func_adl_servicex_xaodr21/__init__.py
func_adl_servicex_xaodr21/_rb_tree_node_base.py
func_adl_servicex_xaodr21/calibration_event_config.py
func_adl_servicex_xaodr21/calibration_support.py
func_adl_servicex_xaodr21/calosampling.py
func_adl_servicex_xaodr21/condition_variable.py
func_adl_servicex_xaodr21/default_calibration_config.py
func_adl_servicex_xaodr21/elementlink_datavector_xaod_btagging_v1__.py
func_adl_servicex_xaodr21/elementlink_datavector_xaod_calocluster_v1__.py
func_adl_servicex_xaodr21/elementlink_datavector_xaod_eventinfo_v1__.py
func_adl_servicex_xaodr21/elementlink_datavector_xaod_iparticle__.py
func_adl_servicex_xaodr21/elementlink_datavector_xaod_jet_v1__.py
func_adl_servicex_xaodr21/elementlink_datavector_xaod_muon_v1__.py
func_adl_servicex_xaodr21/elementlink_datavector_xaod_muonsegment_v1__.py
func_adl_servicex_xaodr21/elementlink_datavector_xaod_neutralparticle_v1__.py
func_adl_servicex_xaodr21/elementlink_datavector_xaod_pfo_v1__.py
func_adl_servicex_xaodr21/elementlink_datavector_xaod_tautrack_v1__.py
func_adl_servicex_xaodr21/elementlink_datavector_xaod_trackmeasurementvalidation_v1__.py
func_adl_servicex_xaodr21/elementlink_datavector_xaod_trackparticle_v1__.py
func_adl_servicex_xaodr21/elementlink_datavector_xaod_truthparticle_v1__.py
func_adl_servicex_xaodr21/elementlink_datavector_xaod_truthvertex_v1__.py
func_adl_servicex_xaodr21/elementlink_datavector_xaod_vertex_v1__.py
func_adl_servicex_xaodr21/event_collection.py
func_adl_servicex_xaodr21/func_adl_iterable.py
func_adl_servicex_xaodr21/ios_base.py
func_adl_servicex_xaodr21/locale.py
func_adl_servicex_xaodr21/metadata_for_collections.py
func_adl_servicex_xaodr21/mutex.py
func_adl_servicex_xaodr21/sx_dataset.py
func_adl_servicex_xaodr21/tcomplex.py
func_adl_servicex_xaodr21/tlorentzvector.py
func_adl_servicex_xaodr21/trigger.py
func_adl_servicex_xaodr21/trotation.py
func_adl_servicex_xaodr21/tsqlresult.py
func_adl_servicex_xaodr21/tsqlrow.py
func_adl_servicex_xaodr21/tthread.py
func_adl_servicex_xaodr21-2.4.4.21.2.283.dist-info/METADATA
func_adl_servicex_xaodr21-2.4.4.21.2.283.dist-info/WHEEL
func_adl_servicex_xaodr21-2.4.4.21.2.283.dist-info/RECORD
