Metadata-Version: 2.4
Name: func_adl_servicex_xaodr21
Version: 2.4.4.21.2.283
Summary: func-adl typed datasets for Servicex for xAOD R21 21.2.283
Project-URL: Source Code, https://github.com/gordonwatts/func_adl_servicex_type_generator
Author-email: Gordon Watts <gwatts@uw.edu>
License: BSD-3-Clause
Classifier: Development Status :: 4 - Beta
Classifier: Intended Audience :: Science/Research
Classifier: License :: OSI Approved :: BSD License
Classifier: Operating System :: OS Independent
Classifier: Programming Language :: Python :: 3
Classifier: Programming Language :: Python :: 3 :: Only
Classifier: Programming Language :: Python :: 3.9
Classifier: Programming Language :: Python :: 3.10
Classifier: Programming Language :: Python :: 3.11
Classifier: Programming Language :: Python :: 3.12
Classifier: Programming Language :: Python :: Implementation :: CPython
Classifier: Topic :: Scientific/Engineering
Classifier: Topic :: Scientific/Engineering :: Physics
Requires-Python: >=3.8
Requires-Dist: servicex>=3.0.0b1
